[
  {
    "Id": 20,
    "UniqueId": "ba837de6-c44a-41ee-ad98-339ac99fa507",
    "EntityVersionId": 11,
    "Name": "Body",
    "Type": {
      "Id": "LargeText",
      "Name": "Large Text",
      "InputType": {
        "Id": "LargeText",
        "Name": "Large Text",
        "ValueType": "String",
        "Length": 2147483647,
        "Icon": "notes"
      }
    },
    "IsDeleted": false,
    "IsRequired": true,
    "IsSearchable": true,
    "IsFilterable": false,
    "IsSortable": false,
    "OrderIndex": 1
  },
  {
    "Id": 48,
    "UniqueId": "3e7f7e4e-e8cb-4479-acae-109d62e8c23d",
    "EntityVersionId": 11,
    "Name": "IsCorrect",
    "Type": {
      "Id": "Text",
      "Name": "Text",
      "InputType": {
        "Id": "Text",
        "Name": "Text",
        "ValueType": "String",
        "Length": 450,
        "Icon": "short_text"
      }
    },
    "IsDeleted": false,
    "IsRequired": false,
    "IsSearchable": false,
    "IsFilterable": false,
    "IsSortable": false,
    "OrderIndex": 4
  }
]